tartarus_lib/__init__.py
tartarus_lib/clients/__init__.py
tartarus_lib/clients/base.py
tartarus_lib/clients/config.py
tartarus_lib/clients/config_definition.py
tartarus_lib/core.py
tartarus_lib/exceptions.py
tartarus_lib-0.1.1.dist-info/METADATA
tartarus_lib-0.1.1.dist-info/WHEEL
tartarus_lib-0.1.1.dist-info/RECORD
