Metadata-Version: 2.3
Name: tartarus-lib
Version: 0.1.1
Summary: Python client library for Tartarus Config Store
License: Apache-2.0
Keywords: config store,Tartarus,Python client
Author: Qreater
Author-email: qreater@gmail.com
Requires-Python: >=3.9,<4.0
Classifier: License :: OSI Approved :: Apache Software License
Classifier: Operating System :: OS Independent
Classifier: Programming Language :: Python :: 3
Classifier: Programming Language :: Python :: 3.9
Classifier: Programming Language :: Python :: 3.10
Classifier: Programming Language :: Python :: 3.11
Classifier: Programming Language :: Python :: 3.12
Classifier: Programming Language :: Python :: 3.13
Requires-Dist: requests (==2.32.3)
